nitrokeyapp/__init__.py
nitrokeyapp/__main__.py
nitrokeyapp/common_ui.py
nitrokeyapp/device_data.py
nitrokeyapp/device_manager.py
nitrokeyapp/device_view.py
nitrokeyapp/error_dialog.py
nitrokeyapp/exceptions.py
nitrokeyapp/gui.py
nitrokeyapp/information_box.py
nitrokeyapp/logger.py
nitrokeyapp/nk3_button.py
nitrokeyapp/overview_tab/__init__.py
nitrokeyapp/overview_tab/worker.py
nitrokeyapp/progress_box.py
nitrokeyapp/prompt_box.py
nitrokeyapp/qt_utils_mix_in.py
nitrokeyapp/secrets_tab/__init__.py
nitrokeyapp/secrets_tab/data.py
nitrokeyapp/secrets_tab/ui.py
nitrokeyapp/secrets_tab/worker.py
nitrokeyapp/settings_tab/__init__.py
nitrokeyapp/settings_tab/worker.py
nitrokeyapp/touch.py
nitrokeyapp/ui/3RDPARTY.txt
nitrokeyapp/ui/LICENSES/GPLv3
nitrokeyapp/ui/LICENSES/LGPLv3
nitrokeyapp/ui/LICENSES/MIT
nitrokeyapp/ui/add_secret_dialog.ui
nitrokeyapp/ui/error_dialog.ui
nitrokeyapp/ui/i18n/CMakeLists.txt
nitrokeyapp/ui/i18n/nitrokey_arabic.qm
nitrokeyapp/ui/i18n/nitrokey_arabic.ts
nitrokeyapp/ui/i18n/nitrokey_de_DE.qm
nitrokeyapp/ui/i18n/nitrokey_de_DE.ts
nitrokeyapp/ui/i18n/nitrokey_en.qm
nitrokeyapp/ui/i18n/nitrokey_en.ts
nitrokeyapp/ui/i18n/nitrokey_fr.qm
nitrokeyapp/ui/i18n/nitrokey_fr.ts
nitrokeyapp/ui/i18n/nitrokey_it.qm
nitrokeyapp/ui/i18n/nitrokey_it.ts
nitrokeyapp/ui/i18n/nitrokey_pl.qm
nitrokeyapp/ui/i18n/nitrokey_pl.ts
nitrokeyapp/ui/icons/HiddenVolumes_0.png
nitrokeyapp/ui/icons/OTP_generate.svg
nitrokeyapp/ui/icons/ProgressWheel.GIF
nitrokeyapp/ui/icons/add_circle.svg
nitrokeyapp/ui/icons/app_logo.svg
nitrokeyapp/ui/icons/black_nitrokey-app-icon.svg
nitrokeyapp/ui/icons/close.svg
nitrokeyapp/ui/icons/content_copy.svg
nitrokeyapp/ui/icons/delete.svg
nitrokeyapp/ui/icons/dialpad.svg
nitrokeyapp/ui/icons/dialpad_off.svg
nitrokeyapp/ui/icons/done.svg
nitrokeyapp/ui/icons/down_arrow.svg
nitrokeyapp/ui/icons/edit.svg
nitrokeyapp/ui/icons/encrypted.svg
nitrokeyapp/ui/icons/help.svg
nitrokeyapp/ui/icons/home.svg
nitrokeyapp/ui/icons/info.svg
nitrokeyapp-2.5.2.dist-info/METADATA
nitrokeyapp-2.5.2.dist-info/WHEEL
nitrokeyapp-2.5.2.dist-info/entry_points.txt
nitrokeyapp-2.5.2.dist-info/licenses/LICENSE
nitrokeyapp-2.5.2.dist-info/RECORD
