Metadata-Version: 2.4
Name: nitrokeyapp
Version: 2.5.2
Summary: Graphical application to manage Nitrokey devices
License-Expression: Apache-2.0
License-File: LICENSE
Author: Nitrokey
Author-email: pypi@nitrokey.com
Requires-Python: >=3.10,<3.15
Classifier: Intended Audience :: Developers
Classifier: Intended Audience :: End Users/Desktop
Classifier: Programming Language :: Python :: 3
Classifier: Programming Language :: Python :: 3.10
Classifier: Programming Language :: Python :: 3.11
Classifier: Programming Language :: Python :: 3.12
Classifier: Programming Language :: Python :: 3.13
Classifier: Programming Language :: Python :: 3.14
Requires-Dist: fido2 (>=2,<3)
Requires-Dist: nitrokey (>=0.4.2,<0.5.0)
Requires-Dist: pySide6 (>=6.6.0)
Requires-Dist: pywin32 (>=305) ; sys_platform == "win32"
Requires-Dist: usb-monitor (>=1.21,<2.0)
